[
  {
    "itemId": "sim_014cbf37",
    "type": "resume",
    "subType": "normal",
    "filename": "simulated_normal_72b8.json",
    "generatedData": {
      "name": "张伟",
      "phone": "13812345678",
      "email": "zhangwei_dev@example.com",
      "education": [
        {
          "school": "苏州大学",
          "degree": "本科",
          "major": "计算机科学与技术",
          "graduationYear": "2019"
        }
      ],
      "experience": [
        {
          "company": "软通动力信息技术（集团）股份有限公司",
          "title": "Java开发工程师",
          "startDate": "2021-07",
          "endDate": "至今",
          "description": "负责电商平台后端核心模块的开发与维护，基于Spring Cloud架构实现微服务治理。通过优化SQL索引和引入Redis缓存，将核心接口响应速度提升了40%。参与了双十一大促期间的系统压测与扩容方案实施。"
        },
        {
          "company": "中软国际科技服务有限公司",
          "title": "初级软件工程师",
          "startDate": "2019-07",
          "endDate": "2021-06",
          "description": "参与甲方通信企业的内部管理系统研发，负责权限管理模块和报表统计模块的编码工作。协助高级工程师进行Bug排查及系统上线后的日常维护。"
        }
      ],
      "skills": [
        "Java",
        "Spring Boot",
        "Spring Cloud",
        "MySQL",
        "Redis",
        "MyBatis-Plus",
        "Docker",
        "Git"
      ],
      "summary": "拥有4年Java后端开发经验的专业人士，熟悉微服务架构与分布式系统设计，具备良好的逻辑思维能力和团队协作精神，能够高效解决生产环境中的技术难题。",
      "expectedSalary": "11000-14000元/月"
    },
    "generatedAt": "2026-03-11T11:54:21.109625+00:00"
  },
  {
    "itemId": "sim_c0ee5158",
    "type": "resume",
    "subType": "missing_education",
    "filename": "simulated_missing_education_b4ef.json",
    "generatedData": {
      "name": "张建国",
      "phone": "13800138000",
      "email": "jianguo.zhang_dev@163.com",
      "education": [],
      "experience": [
        {
          "company": "深圳市拓保软件有限公司",
          "title": "Java开发工程师",
          "startDate": "2020-03",
          "endDate": "2024-05",
          "description": "作为外包开发人员派驻至某大型股份制银行，负责信贷系统后台模块的开发与维护。使用Spring Boot与MyBatis-Plus进行业务逻辑实现，优化了核心审批流程的SQL查询，提升系统响应速度20%。"
        },
        {
          "company": "北京软通动力信息技术有限公司",
          "title": "初级软件工程师",
          "startDate": "2018-06",
          "endDate": "2020-02",
          "description": "参与电商平台后台管理系统的功能迭代，负责商品管理、订单查询等基础模块的编码及单元测试工作。"
        }
      ],
      "skills": [
        "Java",
        "Spring Cloud",
        "MySQL",
        "Redis",
        "Git",
        "Maven"
      ],
      "summary": "拥有6年Java后端开发经验，熟悉微服务架构，具备大型银行项目外包经验，能够快速适应高强度工作环境。因个人证件正在补办中，暂未上传学历证明材料。",
      "expectedSalary": "14000-16000元/月"
    },
    "generatedAt": "2026-03-11T11:54:43.587897+00:00"
  },
  {
    "itemId": "sim_6f0abaf3",
    "type": "resume",
    "subType": "missing_skills",
    "filename": "simulated_missing_skills_2992.json",
    "generatedData": {
      "name": "张伟",
      "phone": "13812345678",
      "email": "zhangwei_work@163.com",
      "education": [
        {
          "school": "武汉工程大学",
          "degree": "本科",
          "major": "计算机科学与技术",
          "graduationYear": "2020"
        }
      ],
      "experience": [
        {
          "company": "武汉众诚信息技术有限公司",
          "title": "软件开发助理",
          "startDate": "2020-07",
          "endDate": "2024-05",
          "description": "主要负责公司内部OA系统的日常维护工作，处理员工反馈的系统操作问题；编写软件使用说明书及技术文档；协助项目经理进行简单的系统测试与环境搭建，确保各部门业务流程的正常流转。"
        }
      ],
      "skills": [
        "熟练使用Microsoft Office系列办公软件",
        "具备良好的文档编写能力",
        "打字录入速度快",
        "沟通能力强",
        "了解计算机基础理论",
        "具备团队协作意识"
      ],
      "summary": "拥有近4年软件开发行业相关工作经验，态度认真负责，擅长技术文档整理与跨部门沟通协作，能够快速适应办公环境。",
      "expectedSalary": "10000-13000元/月"
    },
    "generatedAt": "2026-03-11T11:55:02.598772+00:00"
  },
  {
    "itemId": "sim_5331e3fc",
    "type": "resume",
    "subType": "career_gap",
    "filename": "simulated_career_gap_5572.json",
    "generatedData": {
      "name": "张伟",
      "phone": "13812345678",
      "email": "zhangwei_dev@163.com",
      "education": [
        {
          "school": "武汉工程大学",
          "degree": "本科",
          "major": "计算机科学与技术",
          "graduationYear": "2015"
        }
      ],
      "experience": [
        {
          "company": "上海锐智科技有限公司",
          "title": "高级Java开发工程师",
          "startDate": "2021-06",
          "endDate": "2023-12",
          "description": "负责电商平台后端核心模块的开发与维护，使用Spring Cloud微服务架构，优化系统响应速度，提升了30%的并发处理能力。"
        },
        {
          "company": "武汉众诚信息技术有限公司",
          "title": "Java开发工程师",
          "startDate": "2015-07",
          "endDate": "2018-05",
          "description": "参与企业ERP系统的模块设计与编码，负责数据库表结构设计及SQL性能调优。"
        }
      ],
      "skills": [
        "Java",
        "Spring Boot",
        "MyBatis",
        "MySQL",
        "Redis",
        "RabbitMQ"
      ],
      "summary": "具备5年以上Java开发经验，技术栈扎实。2018年5月至2021年6月期间因处理家庭事务及个人创业尝试离职，现已稳定，可全身心投入职场。",
      "expectedSalary": "15000-18000元/月"
    },
    "generatedAt": "2026-03-11T11:55:19.043781+00:00"
  },
  {
    "itemId": "sim_16955ea2",
    "type": "resume",
    "subType": "strange_degree",
    "filename": "simulated_strange_degree_e00f.json",
    "generatedData": {
      "name": "赵星宇",
      "phone": "13910293847",
      "email": "zhao_xingyu_energy@163.com",
      "education": [
        {
          "school": "环球灵性成长研修学院",
          "degree": "宇宙能量协调硕士",
          "major": "量子磁场与人类行为干预",
          "graduationYear": 2021
        },
        {
          "school": "西安工业大学",
          "degree": "本科",
          "major": "工商管理",
          "graduationYear": 2018
        }
      ],
      "experience": [
        {
          "company": "灵犀文化传播有限公司",
          "title": "高级能量调频顾问",
          "startDate": "2021-07",
          "endDate": "2023-12",
          "description": "负责企业客户的职场磁场分析与员工情绪调频工作。通过量子干预理论优化团队沟通效率，减少部门间协作摩擦，提升整体办公环境的“正向能量流”。"
        },
        {
          "company": "某大型零售贸易公司",
          "title": "人力资源助理",
          "startDate": "2018-07",
          "endDate": "2020-08",
          "description": "负责日常招聘信息的发布与简历初筛，协助组织员工入职培训及社保公积金缴纳业务。"
        }
      ],
      "skills": [
        "磁场分析",
        "NLP心理暗示",
        "情绪压力管理",
        "招聘面试",
        "企业文化建设"
      ],
      "summary": "具备传统HR管理经验与前沿“宇宙能量协调”学术背景的复合型人才，擅长从微观能量角度解决职场冲突。",
      "expectedSalary": "12000-15000元/月"
    },
    "generatedAt": "2026-03-11T11:55:58.539252+00:00"
  },
  {
    "itemId": "sim_254eaa85",
    "type": "resume",
    "subType": "overqualified",
    "filename": "simulated_overqualified_003d.json",
    "generatedData": {
      "name": "赵博远",
      "phone": "13912345678",
      "email": "zhaoboyuan_phd@163.com",
      "education": [
        {
          "school": "清华大学",
          "degree": "博士",
          "major": "计算机科学与技术",
          "graduationYear": 2012
        },
        {
          "school": "清华大学",
          "degree": "本科",
          "major": "计算机科学与技术",
          "graduationYear": 2007
        }
      ],
      "experience": [
        {
          "company": "阿里巴巴集团",
          "title": "资深技术专家 (P8)",
          "startDate": "2018-05",
          "endDate": "2023-10",
          "description": "负责核心交易系统的高可用架构设计与演进，带领50人以上的研发团队。主导双十一大促的系统重构，通过引入云原生架构与自研中间件，将系统峰值QPS提升300%，同时降低了20%的服务器成本。"
        },
        {
          "company": "深圳市腾讯计算机系统有限公司",
          "title": "高级后台开发工程师 / 技术Leader",
          "startDate": "2012-07",
          "endDate": "2018-04",
          "description": "参与微信支付底层基础服务的研发与维护。从零搭建分布式缓存中间件，支撑日均百亿次调用，保障系统99.999%的可用性。"
        }
      ],
      "skills": [
        "分布式架构设计",
        "微服务治理",
        "高并发处理",
        "百人团队管理",
        "Java",
        "Golang",
        "云原生架构",
        "Kubernetes",
        "性能调优"
      ],
      "summary": "清华大学计算机博士，11年一线互联网大厂（阿里、腾讯）核心系统研发与架构经验。曾主导亿级用户规模的分布式系统重构，具备丰富的技术攻坚与大团队管理经验。远超一般外包开发岗位要求，适合作为核心架构师或技术总监引入。",
      "expectedSalary": "35000-50000元/月"
    },
    "generatedAt": "2026-03-11T11:56:31.545352+00:00"
  },
  {
    "itemId": "sim_9d3fba1e",
    "type": "resume",
    "subType": "junior_candidate",
    "filename": "simulated_junior_candidate_520e.json",
    "generatedData": {
      "name": "陈思远",
      "phone": "13800138000",
      "email": "chen_siyuan2024@163.com",
      "education": [
        {
          "school": "武昌工学院",
          "degree": "本科",
          "major": "软件工程",
          "graduationYear": 2024
        }
      ],
      "experience": [
        {
          "company": "武汉众诚信息技术有限公司",
          "title": "软件开发实习生",
          "startDate": "2023-09",
          "endDate": "2024-01",
          "description": "参与公司内部CRM系统的日常维护与小功能开发。主要负责前端页面的简单调整，协助导师编写简单的SQL查询语句，并参与了部分测试用例的执行工作。"
        }
      ],
      "skills": [
        "Java基础",
        "MySQL",
        "HTML5/CSS3",
        "JavaScript",
        "Git"
      ],
      "summary": "2024届应届毕业生，具备扎实的计算机专业基础，学习能力强，对待工作认真负责，希望在技术岗位上不断成长。",
      "expectedSalary": "4000-5000元/月"
    },
    "generatedAt": "2026-03-11T11:56:55.021660+00:00"
  },
  {
    "itemId": "sim_afc62e5f",
    "type": "jd",
    "subType": "normal",
    "filename": "simulated_normal_0bfd.json",
    "generatedData": {
      "title": "Java后端开发工程师",
      "department": "CSIG",
      "applicableClient": "腾讯",
      "requirements": [
        "统招本科及以上学历，计算机科学或相关专业，具备3-5年Java后端实际开发经验",
        "Java基础扎实，深入理解JVM原理、多线程并发编程及网络通信机制",
        "熟练掌握Spring Boot、Spring Cloud、MyBatis等主流开源框架，了解其底层原理",
        "熟悉MySQL数据库体系结构，具备优秀的SQL编写及性能调优能力",
        "熟练使用Redis、Kafka、RocketMQ等常用中间件，并了解其应用场景与限制",
        "具备良好的微服务架构设计经验，有高并发、大流量分布式系统开发经验者优先考虑",
        "具备较强的逻辑思维能力、沟通协作能力及抗压能力，代码规范意识强"
      ],
      "responsibilities": [
        "参与腾讯云相关业务中台系统的需求分析、架构设计与核心模块研发工作",
        "负责编写高质量、高可维护性的后台代码，并完成相应的单元测试",
        "持续优化现有系统的性能，排查并解决线上系统运行中出现的各类疑难问题",
        "保障所负责服务的高可用性、高并发处理能力及整体系统的稳定性",
        "与产品经理、前端开发工程师及测试团队紧密配合，确保业务需求的高质量交付"
      ],
      "salaryRange": "13000-17000元/月",
      "location": "深圳市南山区腾讯海滨大厦",
      "experienceYears": "3-5年"
    },
    "generatedAt": "2026-03-11T11:57:41.565169+00:00",
    "applicableClient": "腾讯"
  },
  {
    "itemId": "sim_22f321d3",
    "type": "jd",
    "subType": "vague_requirements",
    "filename": "simulated_vague_requirements_5295.json",
    "generatedData": {
      "title": "系统研发工程师",
      "department": "PCG",
      "applicableClient": "腾讯",
      "requirements": [
        "统招本科及以上学历，计算机相关专业，具备扎实的技术功底。",
        "精通至少一种主流后端开发语言，熟悉相关生态和流行框架，具备良好的代码习惯。",
        "熟练掌握主流数据库的使用及调优，了解常见中间件的原理及应用场景。",
        "具备优秀的逻辑思维能力和业务抽象能力，能快速理解复杂业务场景并落地。",
        "具备良好的沟通协作能力，皮实抗压，能够拥抱互联网的快速变化，有海量服务经验者优先。"
      ],
      "responsibilities": [
        "负责腾讯相关内容生态业务的底层逻辑梳理与系统开发工作。",
        "参与现有架构的优化与演进，打通各业务线的数据闭环。",
        "配合产品和运营团队，快速响应业务诉求，通过技术赋能业务增长。",
        "解决系统运行过程中的各类疑难杂症，保障海量服务的稳定性与高可用。"
      ],
      "salaryRange": "13000-17000元/月",
      "location": "深圳市南山区科兴科学园",
      "experienceYears": "3-5年"
    },
    "generatedAt": "2026-03-11T11:58:19.549249+00:00",
    "applicableClient": "腾讯"
  },
  {
    "itemId": "sim_1cc5b748",
    "type": "jd",
    "subType": "conflicting_criteria",
    "filename": "simulated_conflicting_criteria_c62d.json",
    "generatedData": {
      "title": "腾讯云后台开发工程师 (CSIG-外包)",
      "department": "CSIG",
      "applicableClient": "腾讯",
      "requirements": [
        "计算机相关专业本科及以上学历，基础扎实",
        "精通Go或C++开发，具备8年以上大型互联网高并发系统架构与研发经验",
        "欢迎2024届优秀应届毕业生投递，有大厂实习经验者优先考虑",
        "深入理解Linux内核、网络协议栈，具备处理亿级QPS场景的性能优化能力",
        "熟练掌握K8s及云原生相关技术，要求有5年以上生产环境大规模集群管理经验",
        "具备极强的学习能力和抗压能力，能够适应腾讯节奏的高强度加班"
      ],
      "responsibilities": [
        "负责腾讯云核心业务模块的后端架构设计、开发与持续优化",
        "参与海量分布式系统的稳定性保障，解决复杂的系统性能瓶颈问题",
        "负责高质量代码编写及技术文档沉淀，推动团队技术进步"
      ],
      "salaryRange": "18000-28000元/月",
      "location": "深圳",
      "experienceYears": "8年以上"
    },
    "generatedAt": "2026-03-11T11:58:54.897857+00:00",
    "applicableClient": "腾讯"
  },
  {
    "itemId": "sim_1109c223",
    "type": "jd",
    "subType": "extreme_salary",
    "filename": "simulated_extreme_salary_467c.json",
    "generatedData": {
      "title": "腾讯TEG-高级后台开发工程师(Go/C++)",
      "department": "TEG",
      "applicableClient": "腾讯",
      "requirements": [
        "本科及以上学历，计算机相关专业，5年以上后台开发经验",
        "精通Go或C++语言，具备扎实的数据结构与算法功底",
        "深入理解Linux内核原理、网络协议栈（TCP/IP）及多线程编程",
        "有大规模分布式系统开发经验，熟悉Raft、Paxos等分布式一致性协议者优先",
        "具备处理海量并发、高可用架构设计能力，能够独立排查复杂的线上技术问题",
        "具备良好的沟通能力和团队协作精神，能适应高强度研发节奏"
      ],
      "responsibilities": [
        "负责腾讯云底层基础设施及分布式存储系统的核心模块研发",
        "参与系统架构设计与性能调优，支撑海量数据的高并发访问需求",
        "编写高质量、可维护的代码，并负责核心代码的Code Review工作",
        "持续优化系统稳定性，通过技术手段提升服务治理水平和运维效率",
        "跟进业界前沿技术，将新技术应用于实际业务场景中"
      ],
      "salaryRange": "32000-38000元/月",
      "location": "深圳腾讯滨海大厦",
      "experienceYears": "5-8年"
    },
    "generatedAt": "2026-03-11T11:59:14.802086+00:00",
    "applicableClient": "腾讯"
  },
  {
    "itemId": "sim_b246c58d",
    "type": "jd",
    "subType": "niche_role",
    "filename": "simulated_niche_role_0d0c.json",
    "generatedData": {
      "title": "核心交易系统重构工程师（Cobol转Go双栈）",
      "department": "CDG",
      "applicableClient": "腾讯",
      "requirements": [
        "统招本科及以上学历，计算机或相关专业，8年以上金融/支付核心系统开发经验。",
        "极度垂直的技术栈要求：必须同时具备5年以上IBM Mainframe环境下大型机COBOL/CICS/DB2开发经验，以及3年以上现代互联网Go语言高并发微服务开发经验。",
        "精通传统银行核心账务系统的底层逻辑，能独立逆向阅读并解析缺乏文档的千万级历史COBOL代码。",
        "深入理解云原生架构，熟练掌握Docker、K8s、Tars框架及TDSQL分布式数据库。",
        "具备极强的跨代际技术栈思维转换能力，有大型金融系统异构迁移或去IOE经验者优先。",
        "能适应金融业务特有的高压环境，接受重大节假日及夜间凌晨的系统割接与护航任务。"
      ],
      "responsibilities": [
        "参与腾讯金融科技（FiT）底层核心支付与清结算系统从传统大型机架构向自研分布式云原生架构的整体迁移工程。",
        "负责对历史遗留的复杂COBOL业务逻辑进行逆向工程，提取核心交易规则并使用Go语言进行微服务化重构。",
        "设计并研发新老异构系统并行运行期间的数据双写、流量回放及高精度资金对账一致性校验组件。",
        "排查并解决跨语言、跨架构迁移过程中的极端并发问题与分布式事务难题，确保重构过程中的绝对零资损。"
      ],
      "salaryRange": "28000-35000元/月",
      "location": "深圳市南山区腾讯滨海大厦",
      "experienceYears": "8年以上"
    },
    "generatedAt": "2026-03-11T11:59:41.425712+00:00",
    "applicableClient": "腾讯"
  },
  {
    "itemId": "sim_c415d17a",
    "type": "resume",
    "subType": "normal",
    "filename": "simulated_normal_828c.json",
    "generatedData": {
      "name": "王丽",
      "phone": "13812345678",
      "email": "wangli.dev@example.com",
      "education": [
        {
          "school": "北京工业大学",
          "degree": "本科",
          "major": "计算机科学与技术",
          "graduationYear": 2020
        }
      ],
      "experience": [
        {
          "company": "某知名互联网公司",
          "title": "后端开发工程师",
          "startDate": "2020-07-01",
          "endDate": "2024-03-31",
          "description": "负责核心业务系统的后端开发与维护，使用Java、Spring Boot框架。参与高并发订单处理系统的设计与实现，优化数据库查询性能，将响应时间缩短20%。与前端团队紧密协作，完成多个新功能模块的接口设计与开发。熟练使用Git进行代码版本管理，参与团队敏捷开发流程。"
        }
      ],
      "skills": [
        "Java",
        "Spring Boot",
        "MySQL",
        "Redis",
        "Kafka",
        "Git",
        "RESTful API",
        "微服务架构",
        "Docker"
      ],
      "summary": "3年后端开发经验，精通Java和Spring Boot，具备独立完成模块设计与开发的能力，熟悉高并发系统优化，致力于提供高性能、高可用的解决方案。",
      "expectedSalary": "12000-15000元/月"
    },
    "generatedAt": "2026-03-13T04:58:35.724646+00:00"
  },
  {
    "itemId": "sim_f73ede57",
    "type": "resume",
    "subType": "normal",
    "filename": "simulated_normal_33ce.json",
    "generatedData": {
      "name": "张强",
      "phone": "13987654321",
      "email": "zhangqiang.data@example.com",
      "education": [
        {
          "school": "武汉工程大学",
          "degree": "本科",
          "major": "统计学",
          "graduationYear": 2018
        }
      ],
      "experience": [
        {
          "company": "某大型电商平台",
          "title": "高级数据分析师",
          "startDate": "2020-08-01",
          "endDate": "2024-03-31",
          "description": "负责用户行为数据分析，构建用户画像，为产品运营提供数据支持。使用SQL、Python进行数据提取、清洗与分析，完成多项专题报告。主导A/B测试设计与结果评估，通过数据驱动优化产品功能，提升用户转化率15%。利用Tableau、Power BI制作数据可视化报表，定期向管理层汇报业务洞察。"
        },
        {
          "company": "某金融科技公司",
          "title": "数据分析师",
          "startDate": "2018-07-01",
          "endDate": "2020-07-31",
          "description": "参与风险控制模型的数据预处理与特征工程。负责日常数据报表生成与异常监控。"
        }
      ],
      "skills": [
        "Python (Pandas, NumPy, Scikit-learn)",
        "SQL",
        "Tableau",
        "Power BI",
        "Excel",
        "数据建模",
        "机器学习基础",
        "A/B测试",
        "统计分析"
      ],
      "summary": "5年数据分析经验，擅长用户行为分析、业务增长策略制定，精通SQL和Python，熟练使用主流数据可视化工具，具备独立解决复杂数据问题的能力。",
      "expectedSalary": "18000-22000元/月"
    },
    "generatedAt": "2026-03-13T04:58:35.724692+00:00"
  },
  {
    "itemId": "sim_110b5fa5",
    "type": "resume",
    "subType": "normal",
    "filename": "simulated_normal_48c7.json",
    "generatedData": {
      "name": "李明",
      "phone": "13700001111",
      "email": "liming.pm@example.com",
      "education": [
        {
          "school": "上海交通大学",
          "degree": "硕士",
          "major": "软件工程",
          "graduationYear": 2022
        }
      ],
      "experience": [
        {
          "company": "某领先科技公司",
          "title": "产品经理",
          "startDate": "2022-07-01",
          "endDate": "2024-03-31",
          "description": "负责企业级SaaS产品的需求调研、竞品分析和产品规划。撰写产品需求文档（PRD），绘制原型图（Axure/Sketch），与研发、设计团队紧密协作。主导产品功能迭代，跟踪上线效果，通过数据分析持续优化用户体验。与客户沟通，收集反馈，将用户需求转化为可落地的产品方案。"
        }
      ],
      "skills": [
        "产品规划",
        "需求分析",
        "原型设计 (Axure, Sketch)",
        "用户研究",
        "市场分析",
        "SQL",
        "项目管理",
        "敏捷开发"
      ],
      "summary": "2年产品经理经验，拥有985/211硕士背景，熟悉产品全生命周期管理，擅长将复杂业务需求转化为清晰的产品方案，具备优秀的沟通协调能力。",
      "expectedSalary": null
    },
    "generatedAt": "2026-03-13T04:58:35.724719+00:00"
  }
]